sqlalchemy_fastapi_endpoint_factory/__init__.py
sqlalchemy_fastapi_endpoint_factory/main.py
sqlalchemy_fastapi_endpoint_factory-1.0.1.dist-info/METADATA
sqlalchemy_fastapi_endpoint_factory-1.0.1.dist-info/WHEEL
sqlalchemy_fastapi_endpoint_factory-1.0.1.dist-info/licenses/LICENSE
sqlalchemy_fastapi_endpoint_factory-1.0.1.dist-info/RECORD
