Metadata-Version: 2.4
Name: sqlalchemy-fastapi-endpoint-factory
Version: 1.0.1
Summary: Auto generate FastAPI endpoint by SqlAlchemy model for data access
Project-URL: Homepage, https://github.com/pavelmaksimov/data-endpoint-factory
Project-URL: Bug Tracker, https://github.com/pavelmaksimov/data-endpoint-factory/issues
Author-email: Pavel Maksimov <vur21@yandex.ru>
License-File: LICENSE
Classifier: License :: OSI Approved :: MIT License
Classifier: Operating System :: OS Independent
Classifier: Programming Language :: Python :: 3
Requires-Python: >=3.10
